<annotation>
	<folder>front_camera</folder>
	<filename>frame_9324.png</filename>
	<path>/home/poker/Desktop/sauvc_dataset/front_camera/frame_9324.png</path>
	<source>
		<database>Unknown</database>
	</source>
	<size>
		<width>648</width>
		<height>488</height>
		<depth>3</depth>
	</size>
	<segmented>0</segmented>
	<object>
		<name>red_bin</name>
		<pose>Unspecified</pose>
		<truncated>0</truncated>
		<difficult>0</difficult>
		<bndbox>
			<xmin>101</xmin>
			<ymin>202</ymin>
			<xmax>140</xmax>
			<ymax>226</ymax>
		</bndbox>
	</object>
	<object>
		<name>red_bin</name>
		<pose>Unspecified</pose>
		<truncated>0</truncated>
		<difficult>0</difficult>
		<bndbox>
			<xmin>190</xmin>
			<ymin>205</ymin>
			<xmax>224</xmax>
			<ymax>226</ymax>
		</bndbox>
	</object>
	<object>
		<name>red_bin</name>
		<pose>Unspecified</pose>
		<truncated>0</truncated>
		<difficult>0</difficult>
		<bndbox>
			<xmin>436</xmin>
			<ymin>205</ymin>
			<xmax>476</xmax>
			<ymax>229</ymax>
		</bndbox>
	</object>
	<object>
		<name>mat</name>
		<pose>Unspecified</pose>
		<truncated>0</truncated>
		<difficult>0</difficult>
		<bndbox>
			<xmin>95</xmin>
			<ymin>215</ymin>
			<xmax>513</xmax>
			<ymax>234</ymax>
		</bndbox>
	</object>
	<object>
		<name>blue_bin</name>
		<pose>Unspecified</pose>
		<truncated>0</truncated>
		<difficult>0</difficult>
		<bndbox>
			<xmin>295</xmin>
			<ymin>206</ymin>
			<xmax>333</xmax>
			<ymax>227</ymax>
		</bndbox>
	</object>
</annotation>
